playlistingscraper/__init__.py
playlistingscraper/playlistingscraper.py
playlistingscraper/version.py
playlistingscraper/xpathExpressions.py
playlistingscraper-0.4.6.dist-info/DESCRIPTION.rst
playlistingscraper-0.4.6.dist-info/entry_points.txt
playlistingscraper-0.4.6.dist-info/METADATA
playlistingscraper-0.4.6.dist-info/metadata.json
playlistingscraper-0.4.6.dist-info/RECORD
playlistingscraper-0.4.6.dist-info/top_level.txt
playlistingscraper-0.4.6.dist-info/WHEEL
