Metadata-Version: 2.0
Name: playlistingscraper
Version: 0.4.6
Summary: A command line tool that scrpaes the listing details of an app in the Google Play Store and saves it in a JSON file.
Home-page: https://github.com/sikuli/sieveable-tools/tree/master/Play-Listing-Scraper
Author: Khalid Alharbi
Author-email: kalharbi@users.noreply.github.com
License: UNKNOWN
Keywords: google,play,scraper,listing,details,apps
Platform: UNKNOWN
Classifier: Development Status :: 4 - Beta
Classifier: Intended Audience :: Science/Research
Classifier: License :: OSI Approved :: MIT License
Classifier: Natural Language :: English
Classifier: Operating System :: OS Independent
Classifier: Programming Language :: Python
Classifier: Programming Language :: Python :: 2.7
Classifier: Topic :: Scientific/Engineering :: Information Analysis
Requires-Dist: lxml (>=3.4.4)
Requires-Dist: requests (>=2.7.0)
